{
    "num_trips": 4,
    "num_stops": 42,
    "bus_capacity": 100,
    "original_dispatch_list": [
        73200,
        73920,
        74640,
        75360
    ],
    "coordinates_list": [
        [
            45.503106,
            -122.418964
        ],
        [
            45.503543,
            -122.426109
        ],
        [
            45.504597,
            -122.436563
        ],
        [
            45.504618,
            -122.441835
        ],
        [
            45.504573,
            -122.449019
        ],
        [
            45.504572,
            -122.462292
        ],
        [
            45.504692,
            -122.477085
        ],
        [
            45.504699,
            -122.484379
        ],
        [
            45.504701,
            -122.490105
        ],
        [
            45.504694,
            -122.496144
        ],
        [
            45.504523,
            -122.502125
        ],
        [
            45.504343,
            -122.51018
        ],
        [
            45.504233,
            -122.516993
        ],
        [
            45.504167,
            -122.525128
        ],
        [
            45.50417,
            -122.529723
        ],
        [
            45.504221,
            -122.53817
        ],
        [
            45.504276,
            -122.54419
        ],
        [
            45.50432,
            -122.548804
        ],
        [
            45.504423,
            -122.560019
        ],
        [
            45.504577,
            -122.567451
        ],
        [
            45.504706,
            -122.575383
        ],
        [
            45.505058,
            -122.579137
        ],
        [
            45.505466,
            -122.586166
        ],
        [
            45.505446,
            -122.594449
        ],
        [
            45.50541,
            -122.602547
        ],
        [
            45.505374,
            -122.610346
        ],
        [
            45.505324,
            -122.618403
        ],
        [
            45.504846,
            -122.62304
        ],
        [
            45.504824,
            -122.630064
        ],
        [
            45.504842,
            -122.634513
        ],
        [
            45.504859,
            -122.639912
        ],
        [
            45.504888,
            -122.645979
        ],
        [
            45.504921,
            -122.655159
        ],
        [
            45.506602,
            -122.663155
        ],
        [
            45.502618,
            -122.671791
        ],
        [
            45.508043,
            -122.679711
        ],
        [
            45.510133,
            -122.682088
        ],
        [
            45.514267,
            -122.681095
        ],
        [
            45.517604,
            -122.679316
        ],
        [
            45.520931,
            -122.677521
        ],
        [
            45.525725,
            -122.676441
        ],
        [
            45.528015,
            -122.675854
        ]
    ],
    "stop_ids_list": [
        "14232",
        "14233",
        "14234",
        "1316",
        "9425",
        "1334",
        "14235",
        "1423",
        "14236",
        "1416",
        "14237",
        "9263",
        "1396",
        "1390",
        "1387",
        "1381",
        "14238",
        "14239",
        "1360",
        "13298",
        "1501",
        "1499",
        "14240",
        "1482",
        "14241",
        "14242",
        "10613",
        "1459",
        "1452",
        "1448",
        "1442",
        "14243",
        "14244",
        "13773",
        "13733",
        "3398",
        "13780",
        "11486",
        "7800",
        "7797",
        "9300",
        "3007"
    ],
    "stop_names_list": [
        "Cleveland Ave Park & Ride",
        "Gresham Central Transit Center",
        "Gresham City Hall Park & Ride",
        "NW Division & Civic Dr",
        "NW Division & Angeline Ave",
        "NW Division & Eastwood Ave",
        "18000 Block SE Division",
        "SE Division & 174th Ave",
        "SE Division & 168th Ave",
        "SE Division & 162nd Ave",
        "SE Division & 157th Ave",
        "SE Division & 148th Ave",
        "SE Division & 142nd Ave",
        "SE Division & 135th Ave",
        "SE Division & 130th Ave",
        "SE Division & 122nd Ave",
        "SE Division & 116th Ave",
        "11100 Block SE Division",
        "SE Division & 101st Ave",
        "SE Division & SE Division St MAX Station",
        "SE Division & 85th Ave",
        "SE Division & 82nd Ave",
        "SE Division & 75th Ave",
        "SE Division & 67th Ave",
        "SE Division & 59th Ave",
        "SE Division & 51st Ave",
        "SE Division & 43rd Ave",
        "SE Division & Cesar Chavez Blvd",
        "SE Division & 34th Ave",
        "SE Division & 30th Ave",
        "SE Division & 26th Ave",
        "SE Division & 20th Ave",
        "SE Division & 11th Ave",
        "OMSI/SE Water",
        "South Waterfront/S Moody",
        "SW Lincoln & 1st",
        "SW Hall & 5th",
        "SW 6th & Columbia",
        "SW 6th & Taylor",
        "SW 6th & Harvey Milk",
        "NW 6th & Flanders",
        "NW Irving & 5th"
    ],
    "dwell_matrix": {
        "1,1": 0,
        "1,2": 15,
        "1,3": 27,
        "1,4": 28,
        "1,5": 4,
        "1,6": 17,
        "1,7": 41,
        "1,8": 5,
        "1,9": 6,
        "1,10": 23,
        "1,11": 22,
        "1,12": 20,
        "1,13": 34,
        "1,14": 20,
        "1,15": 9,
        "1,16": 17,
        "1,17": 36,
        "1,18": 8,
        "1,19": 23,
        "1,20": 6,
        "1,21": 20,
        "1,22": 38,
        "1,23": 41,
        "1,24": 46,
        "1,25": 85,
        "1,26": 31,
        "1,27": 39,
        "1,28": 64,
        "1,29": 51,
        "1,30": 68,
        "1,31": 81,
        "1,32": 112,
        "1,33": 88,
        "1,34": 58,
        "1,35": 196,
        "1,36": 94,
        "1,37": 141,
        "1,38": 142,
        "1,39": 122,
        "1,40": 353,
        "1,41": 319,
        "1,42": 0,
        "2,1": 0,
        "2,2": 18,
        "2,3": 31,
        "2,4": 34,
        "2,5": 5,
        "2,6": 21,
        "2,7": 46,
        "2,8": 6,
        "2,9": 7,
        "2,10": 26,
        "2,11": 24,
        "2,12": 22,
        "2,13": 38,
        "2,14": 22,
        "2,15": 11,
        "2,16": 22,
        "2,17": 43,
        "2,18": 13,
        "2,19": 35,
        "2,20": 10,
        "2,21": 38,
        "2,22": 66,
        "2,23": 69,
        "2,24": 84,
        "2,25": 154,
        "2,26": 57,
        "2,27": 78,
        "2,28": 121,
        "2,29": 90,
        "2,30": 100,
        "2,31": 111,
        "2,32": 136,
        "2,33": 97,
        "2,34": 65,
        "2,35": 196,
        "2,36": 96,
        "2,37": 128,
        "2,38": 130,
        "2,39": 101,
        "2,40": 271,
        "2,41": 214,
        "2,42": 0,
        "3,1": 0,
        "3,2": 17,
        "3,3": 59,
        "3,4": 42,
        "3,5": 6,
        "3,6": 26,
        "3,7": 48,
        "3,8": 6,
        "3,9": 8,
        "3,10": 28,
        "3,11": 29,
        "3,12": 27,
        "3,13": 47,
        "3,14": 33,
        "3,15": 16,
        "3,16": 36,
        "3,17": 65,
        "3,18": 19,
        "3,19": 51,
        "3,20": 15,
        "3,21": 52,
        "3,22": 98,
        "3,23": 107,
        "3,24": 123,
        "3,25": 218,
        "3,26": 77,
        "3,27": 91,
        "3,28": 146,
        "3,29": 107,
        "3,30": 112,
        "3,31": 128,
        "3,32": 154,
        "3,33": 110,
        "3,34": 73,
        "3,35": 206,
        "3,36": 99,
        "3,37": 129,
        "3,38": 120,
        "3,39": 75,
        "3,40": 244,
        "3,41": 191,
        "3,42": 0,
        "4,1": 0,
        "4,2": 29,
        "4,3": 47,
        "4,4": 50,
        "4,5": 7,
        "4,6": 31,
        "4,7": 78,
        "4,8": 10,
        "4,9": 13,
        "4,10": 45,
        "4,11": 46,
        "4,12": 43,
        "4,13": 75,
        "4,14": 45,
        "4,15": 21,
        "4,16": 41,
        "4,17": 84,
        "4,18": 24,
        "4,19": 67,
        "4,20": 19,
        "4,21": 71,
        "4,22": 130,
        "4,23": 132,
        "4,24": 146,
        "4,25": 257,
        "4,26": 90,
        "4,27": 98,
        "4,28": 159,
        "4,29": 115,
        "4,30": 119,
        "4,31": 131,
        "4,32": 150,
        "4,33": 102,
        "4,34": 68,
        "4,35": 181,
        "4,36": 82,
        "4,37": 101,
        "4,38": 106,
        "4,39": 75,
        "4,40": 216,
        "4,41": 175,
        "4,42": 0
    },
    "busload_matrix": {
        "1,1": 0,
        "1,2": 13,
        "1,3": 20,
        "1,4": 15,
        "1,5": 19,
        "1,6": 19,
        "1,7": 14,
        "1,8": 22,
        "1,9": 22,
        "1,10": 20,
        "1,11": 10,
        "1,12": 15,
        "1,13": 18,
        "1,14": 14,
        "1,15": 19,
        "1,16": 20,
        "1,17": 29,
        "1,18": 15,
        "1,19": 14,
        "1,20": 11,
        "1,21": 9,
        "1,22": 15,
        "1,23": 23,
        "1,24": 25,
        "1,25": 41,
        "1,26": 29,
        "1,27": 16,
        "1,28": 35,
        "1,29": 26,
        "1,30": 17,
        "1,31": 40,
        "1,32": 39,
        "1,33": 57,
        "1,34": 82,
        "1,35": 74,
        "1,36": 101,
        "1,37": 101,
        "1,38": 167,
        "1,39": 168,
        "1,40": 221,
        "1,41": 180,
        "1,42": 100,
        "2,1": 0,
        "2,2": 13,
        "2,3": 22,
        "2,4": 17,
        "2,5": 23,
        "2,6": 22,
        "2,7": 17,
        "2,8": 25,
        "2,9": 25,
        "2,10": 23,
        "2,11": 11,
        "2,12": 17,
        "2,13": 20,
        "2,14": 16,
        "2,15": 21,
        "2,16": 23,
        "2,17": 34,
        "2,18": 18,
        "2,19": 18,
        "2,20": 17,
        "2,21": 13,
        "2,22": 27,
        "2,23": 39,
        "2,24": 43,
        "2,25": 74,
        "2,26": 52,
        "2,27": 30,
        "2,28": 67,
        "2,29": 49,
        "2,30": 30,
        "2,31": 61,
        "2,32": 53,
        "2,33": 69,
        "2,34": 95,
        "2,35": 84,
        "2,36": 102,
        "2,37": 102,
        "2,38": 162,
        "2,39": 160,
        "2,40": 203,
        "2,41": 138,
        "2,42": 61,
        "3,1": 0,
        "3,2": 44,
        "3,3": 53,
        "3,4": 35,
        "3,5": 32,
        "3,6": 31,
        "3,7": 22,
        "3,8": 26,
        "3,9": 26,
        "3,10": 24,
        "3,11": 12,
        "3,12": 20,
        "3,13": 24,
        "3,14": 20,
        "3,15": 29,
        "3,16": 33,
        "3,17": 50,
        "3,18": 27,
        "3,19": 27,
        "3,20": 25,
        "3,21": 19,
        "3,22": 38,
        "3,23": 58,
        "3,24": 66,
        "3,25": 110,
        "3,26": 72,
        "3,27": 40,
        "3,28": 83,
        "3,29": 59,
        "3,30": 36,
        "3,31": 70,
        "3,32": 61,
        "3,33": 79,
        "3,34": 108,
        "3,35": 95,
        "3,36": 108,
        "3,37": 106,
        "3,38": 167,
        "3,39": 157,
        "3,40": 187,
        "3,41": 125,
        "3,42": 54,
        "4,1": 0,
        "4,2": 20,
        "4,3": 34,
        "4,4": 27,
        "4,5": 34,
        "4,6": 34,
        "4,7": 25,
        "4,8": 41,
        "4,9": 41,
        "4,10": 39,
        "4,11": 19,
        "4,12": 32,
        "4,13": 39,
        "4,14": 32,
        "4,15": 41,
        "4,16": 46,
        "4,17": 66,
        "4,18": 35,
        "4,19": 36,
        "4,20": 32,
        "4,21": 25,
        "4,22": 51,
        "4,23": 77,
        "4,24": 83,
        "4,25": 134,
        "4,26": 84,
        "4,27": 47,
        "4,28": 93,
        "4,29": 64,
        "4,30": 38,
        "4,31": 74,
        "4,32": 62,
        "4,33": 76,
        "4,34": 102,
        "4,35": 89,
        "4,36": 95,
        "4,37": 91,
        "4,38": 138,
        "4,39": 134,
        "4,40": 165,
        "4,41": 110,
        "4,42": 51
    },
    "arrival_matrix": {
        "1,2": 73351,
        "1,3": 73456,
        "1,4": 73633,
        "1,5": 73720,
        "1,6": 73784,
        "1,7": 73927,
        "1,8": 74088,
        "1,9": 74153,
        "1,10": 74220,
        "1,11": 74273,
        "1,12": 74354,
        "1,13": 74431,
        "1,14": 74525,
        "1,15": 74605,
        "1,16": 74677,
        "1,17": 74785,
        "1,18": 74851,
        "1,19": 74889,
        "1,20": 75003,
        "1,21": 75068,
        "1,22": 75178,
        "1,23": 75246,
        "1,24": 75350,
        "1,25": 75426,
        "1,26": 75541,
        "1,27": 75631,
        "1,28": 75764,
        "1,29": 75920,
        "1,30": 76068,
        "1,31": 76226,
        "1,32": 76336,
        "1,33": 76511,
        "1,34": 76656,
        "1,35": 76864,
        "1,36": 77177,
        "1,37": 77392,
        "1,38": 77596,
        "1,39": 77918,
        "1,40": 78097,
        "1,41": 78540,
        "1,42": 79069,
        "2,2": 73700,
        "2,3": 73807,
        "2,4": 74019,
        "2,5": 74110,
        "2,6": 74175,
        "2,7": 74285,
        "2,8": 74421,
        "2,9": 74457,
        "2,10": 74494,
        "2,11": 74586,
        "2,12": 74670,
        "2,13": 74751,
        "2,14": 74821,
        "2,15": 74903,
        "2,16": 74973,
        "2,17": 75085,
        "2,18": 75188,
        "2,19": 75231,
        "2,20": 75359,
        "2,21": 75429,
        "2,22": 75528,
        "2,23": 75624,
        "2,24": 75771,
        "2,25": 75915,
        "2,26": 76138,
        "2,27": 76252,
        "2,28": 76391,
        "2,29": 76571,
        "2,30": 76752,
        "2,31": 76909,
        "2,32": 77080,
        "2,33": 77277,
        "2,34": 77464,
        "2,35": 77740,
        "2,36": 78054,
        "2,37": 78274,
        "2,38": 78551,
        "2,39": 78893,
        "2,40": 79023,
        "2,41": 79384,
        "2,42": 79779,
        "3,2": 74039,
        "3,3": 74179,
        "3,4": 74358,
        "3,5": 74460,
        "3,6": 74496,
        "3,7": 74613,
        "3,8": 74751,
        "3,9": 74816,
        "3,10": 74890,
        "3,11": 74974,
        "3,12": 75072,
        "3,13": 75160,
        "3,14": 75282,
        "3,15": 75375,
        "3,16": 75451,
        "3,17": 75547,
        "3,18": 75671,
        "3,19": 75720,
        "3,20": 75858,
        "3,21": 75933,
        "3,22": 76075,
        "3,23": 76234,
        "3,24": 76401,
        "3,25": 76584,
        "3,26": 76862,
        "3,27": 77002,
        "3,28": 77153,
        "3,29": 77364,
        "3,30": 77534,
        "3,31": 77736,
        "3,32": 77924,
        "3,33": 78138,
        "3,34": 78338,
        "3,35": 78621,
        "3,36": 78927,
        "3,37": 79149,
        "3,38": 79338,
        "3,39": 79608,
        "3,40": 79771,
        "3,41": 80046,
        "3,42": 80357,
        "4,2": 74606,
        "4,3": 74725,
        "4,4": 74922,
        "4,5": 75032,
        "4,6": 75101,
        "4,7": 75222,
        "4,8": 75381,
        "4,9": 75450,
        "4,10": 75523,
        "4,11": 75595,
        "4,12": 75701,
        "4,13": 75778,
        "4,14": 75881,
        "4,15": 75956,
        "4,16": 76006,
        "4,17": 76137,
        "4,18": 76311,
        "4,19": 76366,
        "4,20": 76499,
        "4,21": 76618,
        "4,22": 76805,
        "4,23": 76971,
        "4,24": 77167,
        "4,25": 77376,
        "4,26": 77694,
        "4,27": 77813,
        "4,28": 77971,
        "4,29": 78197,
        "4,30": 78371,
        "4,31": 78551,
        "4,32": 78741,
        "4,33": 78951,
        "4,34": 79146,
        "4,35": 79392,
        "4,36": 79633,
        "4,37": 79863,
        "4,38": 80084,
        "4,39": 80310,
        "4,40": 80445,
        "4,41": 80723,
        "4,42": 81072
    },
    "headway_matrix": {
        "1,2": 276,
        "1,3": 291,
        "1,4": 300,
        "1,5": 309,
        "1,6": 301,
        "1,7": 318,
        "1,8": 329,
        "1,9": 300,
        "1,10": 281,
        "1,11": 304,
        "1,12": 291,
        "1,13": 290,
        "1,14": 276,
        "1,15": 272,
        "1,16": 251,
        "1,17": 239,
        "1,18": 221,
        "1,19": 169,
        "1,20": 192,
        "1,21": 198,
        "1,22": 187,
        "1,23": 225,
        "1,24": 242,
        "1,25": 246,
        "1,26": 301,
        "1,27": 301,
        "1,28": 332,
        "1,29": 380,
        "1,30": 431,
        "1,31": 499,
        "1,32": 579,
        "1,33": 661,
        "1,34": 719,
        "1,35": 777,
        "1,36": 936,
        "1,37": 851,
        "1,38": 962,
        "1,39": 1073,
        "1,40": 1153,
        "1,41": 1437,
        "1,42": 1720,
        "2,2": 348,
        "2,3": 351,
        "2,4": 386,
        "2,5": 389,
        "2,6": 390,
        "2,7": 358,
        "2,8": 333,
        "2,9": 304,
        "2,10": 273,
        "2,11": 313,
        "2,12": 315,
        "2,13": 320,
        "2,14": 295,
        "2,15": 298,
        "2,16": 296,
        "2,17": 301,
        "2,18": 338,
        "2,19": 342,
        "2,20": 356,
        "2,21": 361,
        "2,22": 350,
        "2,23": 378,
        "2,24": 421,
        "2,25": 490,
        "2,26": 598,
        "2,27": 621,
        "2,28": 627,
        "2,29": 651,
        "2,30": 685,
        "2,31": 684,
        "2,32": 744,
        "2,33": 766,
        "2,34": 808,
        "2,35": 876,
        "2,36": 877,
        "2,37": 882,
        "2,38": 956,
        "2,39": 975,
        "2,40": 926,
        "2,41": 845,
        "2,42": 710,
        "3,2": 339,
        "3,3": 372,
        "3,4": 339,
        "3,5": 350,
        "3,6": 321,
        "3,7": 328,
        "3,8": 329,
        "3,9": 359,
        "3,10": 396,
        "3,11": 389,
        "3,12": 402,
        "3,13": 409,
        "3,14": 461,
        "3,15": 472,
        "3,16": 478,
        "3,17": 462,
        "3,18": 483,
        "3,19": 489,
        "3,20": 499,
        "3,21": 504,
        "3,22": 547,
        "3,23": 610,
        "3,24": 630,
        "3,25": 669,
        "3,26": 724,
        "3,27": 750,
        "3,28": 762,
        "3,29": 792,
        "3,30": 781,
        "3,31": 826,
        "3,32": 843,
        "3,33": 861,
        "3,34": 874,
        "3,35": 880,
        "3,36": 873,
        "3,37": 875,
        "3,38": 786,
        "3,39": 715,
        "3,40": 748,
        "3,41": 661,
        "3,42": 578,
        "4,2": 567,
        "4,3": 546,
        "4,4": 564,
        "4,5": 572,
        "4,6": 605,
        "4,7": 609,
        "4,8": 630,
        "4,9": 634,
        "4,10": 633,
        "4,11": 620,
        "4,12": 629,
        "4,13": 617,
        "4,14": 600,
        "4,15": 582,
        "4,16": 555,
        "4,17": 590,
        "4,18": 640,
        "4,19": 646,
        "4,20": 641,
        "4,21": 685,
        "4,22": 730,
        "4,23": 738,
        "4,24": 766,
        "4,25": 792,
        "4,26": 832,
        "4,27": 811,
        "4,28": 818,
        "4,29": 833,
        "4,30": 838,
        "4,31": 815,
        "4,32": 818,
        "4,33": 813,
        "4,34": 808,
        "4,35": 772,
        "4,36": 706,
        "4,37": 714,
        "4,38": 746,
        "4,39": 702,
        "4,40": 674,
        "4,41": 677,
        "4,42": 715
    },
    "stranded_matrix": {
        "1,1": 0,
        "1,2": 0,
        "1,3": 0,
        "1,4": 0,
        "1,5": 0,
        "1,6": 0,
        "1,7": 0,
        "1,8": 0,
        "1,9": 0,
        "1,10": 0,
        "1,11": 0,
        "1,12": 0,
        "1,13": 0,
        "1,14": 0,
        "1,15": 0,
        "1,16": 0,
        "1,17": 0,
        "1,18": 0,
        "1,19": 0,
        "1,20": 0,
        "1,21": 0,
        "1,22": 0,
        "1,23": 0,
        "1,24": 0,
        "1,25": 0,
        "1,26": 0,
        "1,27": 0,
        "1,28": 0,
        "1,29": 0,
        "1,30": 0,
        "1,31": 0,
        "1,32": 0,
        "1,33": 0,
        "1,34": 0,
        "1,35": 0,
        "1,36": 0,
        "1,37": 0,
        "1,38": 0,
        "1,39": 0,
        "1,40": 0,
        "1,41": 0,
        "1,42": 0,
        "2,1": 0,
        "2,2": 0,
        "2,3": 0,
        "2,4": 0,
        "2,5": 0,
        "2,6": 0,
        "2,7": 0,
        "2,8": 0,
        "2,9": 0,
        "2,10": 0,
        "2,11": 0,
        "2,12": 0,
        "2,13": 0,
        "2,14": 0,
        "2,15": 0,
        "2,16": 0,
        "2,17": 0,
        "2,18": 0,
        "2,19": 0,
        "2,20": 0,
        "2,21": 0,
        "2,22": 0,
        "2,23": 0,
        "2,24": 0,
        "2,25": 0,
        "2,26": 0,
        "2,27": 0,
        "2,28": 0,
        "2,29": 0,
        "2,30": 0,
        "2,31": 0,
        "2,32": 0,
        "2,33": 0,
        "2,34": 0,
        "2,35": 0,
        "2,36": 0,
        "2,37": 0,
        "2,38": 0,
        "2,39": 0,
        "2,40": 0,
        "2,41": 0,
        "2,42": 0,
        "3,1": 0,
        "3,2": 0,
        "3,3": 0,
        "3,4": 0,
        "3,5": 0,
        "3,6": 0,
        "3,7": 0,
        "3,8": 0,
        "3,9": 0,
        "3,10": 0,
        "3,11": 0,
        "3,12": 0,
        "3,13": 0,
        "3,14": 0,
        "3,15": 0,
        "3,16": 0,
        "3,17": 0,
        "3,18": 0,
        "3,19": 0,
        "3,20": 0,
        "3,21": 0,
        "3,22": 0,
        "3,23": 0,
        "3,24": 0,
        "3,25": 0,
        "3,26": 0,
        "3,27": 0,
        "3,28": 0,
        "3,29": 0,
        "3,30": 0,
        "3,31": 0,
        "3,32": 0,
        "3,33": 0,
        "3,34": 0,
        "3,35": 0,
        "3,36": 0,
        "3,37": 0,
        "3,38": 0,
        "3,39": 0,
        "3,40": 0,
        "3,41": 0,
        "3,42": 0,
        "4,1": 0,
        "4,2": 0,
        "4,3": 0,
        "4,4": 0,
        "4,5": 0,
        "4,6": 0,
        "4,7": 0,
        "4,8": 0,
        "4,9": 0,
        "4,10": 0,
        "4,11": 0,
        "4,12": 0,
        "4,13": 0,
        "4,14": 0,
        "4,15": 0,
        "4,16": 0,
        "4,17": 0,
        "4,18": 0,
        "4,19": 0,
        "4,20": 0,
        "4,21": 0,
        "4,22": 0,
        "4,23": 0,
        "4,24": 0,
        "4,25": 0,
        "4,26": 0,
        "4,27": 0,
        "4,28": 0,
        "4,29": 0,
        "4,30": 0,
        "4,31": 0,
        "4,32": 0,
        "4,33": 0,
        "4,34": 0,
        "4,35": 0,
        "4,36": 0,
        "4,37": 0,
        "4,38": 0,
        "4,39": 0,
        "4,40": 0,
        "4,41": 0,
        "4,42": 0
    },
    "dispatch_list": {
        "1": 72686,
        "2": 72978,
        "3": 73952,
        "4": 74383
    },
    "objective_value": 1806.6759270883745
}